SimpleCopy/__init__.py
SimpleCopy/code_copy.py
SimpleCopy/code_exceptions.py
SimpleCopy/code_move.py
SimpleCopy/code_zip.py
SimpleCopy-0.0.2.dist-info/LICENSE
SimpleCopy-0.0.2.dist-info/METADATA
SimpleCopy-0.0.2.dist-info/WHEEL
SimpleCopy-0.0.2.dist-info/top_level.txt
SimpleCopy-0.0.2.dist-info/RECORD
